MANIFEST.in
requirements.txt
setup.py
basic_sdk/__init__.py
basic_sdk/__main__.py
basic_sdk/authority.py
basic_sdk/exceptions.py
basic_sdk/func.py
basic_sdk/http.py
basic_sdk/model.py
basic_sdk/openapi.py
basic_sdk/permission.py
basic_sdk/router.py
basic_sdk/schema.py
basic_sdk.egg-info/PKG-INFO
basic_sdk.egg-info/SOURCES.txt
basic_sdk.egg-info/dependency_links.txt
basic_sdk.egg-info/not-zip-safe
basic_sdk.egg-info/requires.txt
basic_sdk.egg-info/top_level.txt