Metadata-Version: 2.1
Name: basic-sdk
Version: 0.0.1
Summary: General project functions
Home-page: https://github.com/Duanxinxin/basic_sdk
Author: dgz
License: UNKNOWN
Platform: UNKNOWN
